Workbook

Sheet オファーリスト
C1: 更新日：2025/12/24 | F1: SJOSP記載欄
C2: 起案者 | F2: 商品コードのセルの色 | M2: SECRET：C
C3: SJOSP | G3: 新規取得 | M3: 作成者 | N3: 起案者と同一
G4: 構成変更 | M4: 作成日 | N4: =D5 -> 0 | O4: ←D５セルより計算式で引っ張ってます
C5: 作成日 | G5: 既存流用 | M5: 廃棄日 | N5: 作成日より一年
C6: 起案者Section名
C7: 起案者名 | F7: オファー表現 メディア限定の有無
C8: 放映・出稿・アップ 開始予定日 | F8: 限定セット
A9: 要 | C9: コード取得完了予定日 | E9: 依頼から、基本3週間目目取得完了 | F9: 限定価格
C10: コード精査担当者 | F10: ※FY22法務オファー新ルールにより、メディア限定表現をしているかどうか
E11: ※すべて税込み価格で記載
C12: チャネル名 | D12: オファー詳細 | G12: WEB：施策名 | H12: プリント：素材コード | K12: TV：素材コード | N12: アプグレードあり/なし
B15: 【メイン販売オファー：主商品（1枚セットなど）】
C16: ★入力 | F16: ★入力 | G16: 自動反映 | H16: ★入力 | I16: 自動反映 | J16: 自動反映 | K16: 自動反映 | L16: 自動反映 | M16: 自動反映 | N16: ★入力 | O16: 自動反映 | P16: ★入力 | Q16: 自動反映 | R16: 自動反映 | S16: 自動反映 | T16: 自動反映 | U16: 自動反映 | V16: 自動反映 | W16: 自動反映 | X16: ★入力 | Y16: プルダウン | Z16: プルダウン | AA16: プルダウン | AB16: プルダウン | AC16: プルダウン | AD16: プルダウン | AE16: プルダウン | AF16: プルダウン | AG16: プルダウン | AH16: ★入力 | AI16: プルダウン | AJ16: ★入力 | AK16: ★入力 | AL16: ★入力 | AM16: ★入力 | AN16: プルダウン | AO16: プルダウン | AP16: ★入力 | AQ16: ★入力 | AR16: プルダウン | AS16: ★入力 | AT16: プルダウン | AU16: ★入力 | AV16: ★入力 | AW16: ★入力
I17: 単品価格 | K17: 単品合計価格 | M17: 販売価格 | O17: VU価格 | Q17: 割引内容 単品合計価格⇒販売価格 | T17: 割引内容 販売価格⇒VU価格 | W17: 送料 | Y17: 返品関連 | AA17: その他 | AF17: 定期商品 | AN17: キャッシュバック | AT17: 超分割 ※9,000円以下(送料込み・税込み)は不可 ※送料込みの価格
A18: ｺｰﾄﾞ数 | B18: 文字数 | C18: 商品グループ | D18: 商品コード ※8文字まで | E18: 商品名（カタカナ・数値は半角のみ可） ※40文字まで（全角は2文字、半角は1文字） | F18: SKU | G18: SKU名 | H18: 数量 | I18: 税抜 | J18: 税込 | K18: 税抜 | L18: 税込 | M18: 税抜 | N18: 税込 | O18: 税抜 | P18: 税込 | Q18: 割引率 | R18: 割引額 （税抜） | S18: 割引額 (税込） | T18: 割引率 | U18: 割引額 （税抜） | V18: 割引額 (税込） | W18: 税抜 | X18: 税込 | Y18: 返品不可区分 | Z18: 返品期間 | AA18: 消費税区分 | AB18: 翌日配送 フラグ | AC18: 【AT/OM補正】 | AD18: 【クレジット分割払】 | AE18: 【ゆうパケ フラグ】 | AF18: 有/無 | AG18: 定期商品種別 | AH18: 定期T2注文品番 | AI18: デフォルトお届け間隔 | AJ18: デフォルトお届け間隔数 | AK18: 初期の間隔 | AL18: 継続商品の注文品番 | AM18: 継続商品の販売価格（税抜） | AN18: キャッシュバック情報登録 | AO18: キャッシュバック対象フラグ | AP18: キャッシュバック 受付期間 | AQ18: キャッシュバック 金額 | AR18: キャッシュバック 単位 | AS18: キャッシュバック 条件 | AT18: ショッピング クレジット (WEBのみ) | AU18: 支払回数 (WEBのみ) | AV18: 初月 (WEBのみ) | AW18: 次月以降 (WEBのみ)
A19: =LENB(D19) -> 0 | B19: =LENB(E19) -> 0 | K19: =SUM(K20:K27) -> 0 | L19: =SUM(L20:L27) -> 0 | M19: =ROUNDUP(N19/1.1,0) -> 0 | O19: =ROUNDUP(P19/1.1,0) -> 0 | Q19: =1-(N19/L19) -> #DIV/0! | R19: =K19-M19 -> 0 | S19: =L19-N19 -> 0 | T19: =1-(P19/N19) -> #DIV/0! | U19: =M19-O19 -> 0 | V19: =N19-P19 -> 0 | W19: =ROUNDUP(X19/1.1,0) -> 0
G20: =IFERROR(VLOOKUP(F20,[4]EX0054_在庫表!$A:$B,2,FALSE),"") | I20: =IFERROR(VLOOKUP(F20,[5]入力シート!$C:$AH,18,FALSE),0) | J20: =ROUNDDOWN(I20*1.1,0) -> 0 | K20: =IFERROR((I20*H20),"") -> 0 | L20: =IFERROR((J20*H20),"") -> 0
G21: =IFERROR(VLOOKUP(F21,[4]EX0054_在庫表!$A:$B,2,FALSE),"") | I21: =IFERROR(VLOOKUP(F21,[5]入力シート!$C:$AH,18,FALSE),0) | J21: =ROUNDDOWN(I21*1.1,0) -> 0 | K21: =IFERROR((I21*H21),"") -> 0 | L21: =IFERROR((J21*H21),"") -> 0
G22: =IFERROR(VLOOKUP(F22,[4]EX0054_在庫表!$A:$B,2,FALSE),"") | I22: =IFERROR(VLOOKUP(F22,[5]入力シート!$C:$AH,18,FALSE),0) | J22: =ROUNDDOWN(I22*1.1,0) -> 0 | K22: =IFERROR((I22*H22),"") -> 0 | L22: =IFERROR((J22*H22),"") -> 0
G23: =IFERROR(VLOOKUP(F23,[4]EX0054_在庫表!$A:$B,2,FALSE),"") | I23: =IFERROR(VLOOKUP(F23,[5]入力シート!$C:$AH,18,FALSE),0) | J23: =ROUNDDOWN(I23*1.1,0) -> 0 | K23: =IFERROR((I23*H23),"") -> 0 | L23: =IFERROR((J23*H23),"") -> 0
G24: =IFERROR(VLOOKUP(F24,[4]EX0054_在庫表!$A:$B,2,FALSE),"") | I24: =IFERROR(VLOOKUP(F24,[5]入力シート!$C:$AH,18,FALSE),0) | J24: =ROUNDDOWN(I24*1.1,0) -> 0 | K24: =IFERROR((I24*H24),"") -> 0 | L24: =IFERROR((J24*H24),"") -> 0
G25: =IFERROR(VLOOKUP(F25,[4]EX0054_在庫表!$A:$B,2,FALSE),"") | I25: =IFERROR(VLOOKUP(F25,[5]入力シート!$C:$AH,18,FALSE),0) | J25: =ROUNDDOWN(I25*1.1,0) -> 0 | K25: =IFERROR((I25*H25),"") -> 0 | L25: =IFERROR((J25*H25),"") -> 0
G26: =IFERROR(VLOOKUP(F26,[4]EX0054_在庫表!$A:$B,2,FALSE),"") | I26: =IFERROR(VLOOKUP(F26,[5]入力シート!$C:$AH,18,FALSE),0) | J26: =ROUNDDOWN(I26*1.1,0) -> 0 | K26: =IFERROR((I26*H26),"") -> 0 | L26: =IFERROR((J26*H26),"") -> 0
G27: =IFERROR(VLOOKUP(F27,[4]EX0054_在庫表!$A:$B,2,FALSE),"") | I27: =IFERROR(VLOOKUP(F27,[5]入力シート!$C:$AH,18,FALSE),0) | J27: =ROUNDDOWN(I27*1.1,0) -> 0 | K27: =IFERROR((I27*H27),"") -> 0 | L27: =IFERROR((J27*H27),"") -> 0
A28: =LENB(D28) -> 0 | B28: =LENB(E28) -> 0 | K28: =SUM(K29:K36) -> 0 | L28: =SUM(L29:L36) -> 0 | M28: =ROUNDUP(N28/1.1,0) -> 0 | O28: =ROUNDUP(P28/1.1,0) -> 0 | Q28: =1-(N28/L28) -> #DIV/0! | R28: =K28-M28 -> 0 | S28: =L28-N28 -> 0 | T28: =1-(P28/N28) -> #DIV/0! | U28: =M28-O28 -> 0 | V28: =N28-P28 -> 0 | W28: =ROUNDUP(X28/1.1,0) -> 0
I29: 0 | J29: =ROUNDDOWN(I29*1.1,0) -> 0 | K29: =IFERROR((I29*H29),"") -> 0 | L29: =IFERROR((J29*H29),"") -> 0
I30: 0 | J30: =ROUNDDOWN(I30*1.1,0) -> 0 | K30: =IFERROR((I30*H30),"") -> 0 | L30: =IFERROR((J30*H30),"") -> 0
I31: 0 | J31: =ROUNDDOWN(I31*1.1,0) -> 0 | K31: =IFERROR((I31*H31),"") -> 0 | L31: =IFERROR((J31*H31),"") -> 0
I32: 0 | J32: =ROUNDDOWN(I32*1.1,0) -> 0 | K32: =IFERROR((I32*H32),"") -> 0 | L32: =IFERROR((J32*H32),"") -> 0
I33: 0 | J33: =ROUNDDOWN(I33*1.1,0) -> 0 | K33: =IFERROR((I33*H33),"") -> 0 | L33: =IFERROR((J33*H33),"") -> 0
I34: 0 | J34: =ROUNDDOWN(I34*1.1,0) -> 0 | K34: =IFERROR((I34*H34),"") -> 0 | L34: =IFERROR((J34*H34),"") -> 0
I35: 0 | J35: =ROUNDDOWN(I35*1.1,0) -> 0 | K35: =IFERROR((I35*H35),"") -> 0 | L35: =IFERROR((J35*H35),"") -> 0
I36: 0 | J36: =ROUNDDOWN(I36*1.1,0) -> 0 | K36: =IFERROR((I36*H36),"") -> 0 | L36: =IFERROR((J36*H36),"") -> 0
A37: =LENB(D37) -> 0 | B37: =LENB(E37) -> 0 | K37: =SUM(K38:K45) -> 0 | L37: =SUM(L38:L45) -> 0 | M37: =ROUNDUP(N37/1.1,0) -> 0 | O37: =ROUNDUP(P37/1.1,0) -> 0 | Q37: =1-(N37/L37) -> #DIV/0! | R37: =K37-M37 -> 0 | S37: =L37-N37 -> 0 | T37: =1-(P37/N37) -> #DIV/0! | U37: =M37-O37 -> 0 | V37: =N37-P37 -> 0 | W37: =ROUNDUP(X37/1.1,0) -> 0
I38: 0 | J38: =ROUNDDOWN(I38*1.1,0) -> 0 | K38: =IFERROR((I38*H38),"") -> 0 | L38: =IFERROR((J38*H38),"") -> 0
I39: 0 | J39: =ROUNDDOWN(I39*1.1,0) -> 0 | K39: =IFERROR((I39*H39),"") -> 0 | L39: =IFERROR((J39*H39),"") -> 0
I40: 0 | J40: =ROUNDDOWN(I40*1.1,0) -> 0 | K40: =IFERROR((I40*H40),"") -> 0 | L40: =IFERROR((J40*H40),"") -> 0
I41: 0 | J41: =ROUNDDOWN(I41*1.1,0) -> 0 | K41: =IFERROR((I41*H41),"") -> 0 | L41: =IFERROR((J41*H41),"") -> 0
I42: 0 | J42: =ROUNDDOWN(I42*1.1,0) -> 0 | K42: =IFERROR((I42*H42),"") -> 0 | L42: =IFERROR((J42*H42),"") -> 0
I43: 0 | J43: =ROUNDDOWN(I43*1.1,0) -> 0 | K43: =IFERROR((I43*H43),"") -> 0 | L43: =IFERROR((J43*H43),"") -> 0
I44: 0 | J44: =ROUNDDOWN(I44*1.1,0) -> 0 | K44: =IFERROR((I44*H44),"") -> 0 | L44: =IFERROR((J44*H44),"") -> 0
I45: 0 | J45: =ROUNDDOWN(I45*1.1,0) -> 0 | K45: =IFERROR((I45*H45),"") -> 0 | L45: =IFERROR((J45*H45),"") -> 0
A46: =LENB(D46) -> 0 | B46: =LENB(E46) -> 0 | K46: =SUM(K47:K54) -> 0 | L46: =SUM(L47:L54) -> 0 | M46: =ROUNDUP(N46/1.1,0) -> 0 | O46: =ROUNDUP(P46/1.1,0) -> 0 | Q46: =1-(N46/L46) -> #DIV/0! | R46: =K46-M46 -> 0 | S46: =L46-N46 -> 0 | T46: =1-(P46/N46) -> #DIV/0! | U46: =M46-O46 -> 0 | V46: =N46-P46 -> 0 | W46: =ROUNDUP(X46/1.1,0) -> 0
I47: 0 | J47: =ROUNDDOWN(I47*1.1,0) -> 0 | K47: =IFERROR((I47*H47),"") -> 0 | L47: =IFERROR((J47*H47),"") -> 0
I48: 0 | J48: =ROUNDDOWN(I48*1.1,0) -> 0 | K48: =IFERROR((I48*H48),"") -> 0 | L48: =IFERROR((J48*H48),"") -> 0
I49: 0 | J49: =ROUNDDOWN(I49*1.1,0) -> 0 | K49: =IFERROR((I49*H49),"") -> 0 | L49: =IFERROR((J49*H49),"") -> 0
I50: 0 | J50: =ROUNDDOWN(I50*1.1,0) -> 0 | K50: =IFERROR((I50*H50),"") -> 0 | L50: =IFERROR((J50*H50),"") -> 0
I51: 0 | J51: =ROUNDDOWN(I51*1.1,0) -> 0 | K51: =IFERROR((I51*H51),"") -> 0 | L51: =IFERROR((J51*H51),"") -> 0
I52: 0 | J52: =ROUNDDOWN(I52*1.1,0) -> 0 | K52: =IFERROR((I52*H52),"") -> 0 | L52: =IFERROR((J52*H52),"") -> 0
I53: 0 | J53: =ROUNDDOWN(I53*1.1,0) -> 0 | K53: =IFERROR((I53*H53),"") -> 0 | L53: =IFERROR((J53*H53),"") -> 0
I54: 0 | J54: =ROUNDDOWN(I54*1.1,0) -> 0 | K54: =IFERROR((I54*H54),"") -> 0 | L54: =IFERROR((J54*H54),"") -> 0
A55: =LENB(D55) -> 0 | B55: =LENB(E55) -> 0 | K55: =SUM(K56:K63) -> 0 | L55: =SUM(L56:L63) -> 0 | M55: =ROUNDUP(N55/1.1,0) -> 0 | O55: =ROUNDUP(P55/1.1,0) -> 0 | Q55: =1-(N55/L55) -> #DIV/0! | R55: =K55-M55 -> 0 | S55: =L55-N55 -> 0 | T55: =1-(P55/N55) -> #DIV/0! | U55: =M55-O55 -> 0 | V55: =N55-P55 -> 0 | W55: =ROUNDUP(X55/1.1,0) -> 0
I56: 0 | J56: =ROUNDDOWN(I56*1.1,0) -> 0 | K56: =IFERROR((I56*H56),"") -> 0 | L56: =IFERROR((J56*H56),"") -> 0
I57: 0 | J57: =ROUNDDOWN(I57*1.1,0) -> 0 | K57: =IFERROR((I57*H57),"") -> 0 | L57: =IFERROR((J57*H57),"") -> 0
I58: 0 | J58: =ROUNDDOWN(I58*1.1,0) -> 0 | K58: =IFERROR((I58*H58),"") -> 0 | L58: =IFERROR((J58*H58),"") -> 0
I59: 0 | J59: =ROUNDDOWN(I59*1.1,0) -> 0 | K59: =IFERROR((I59*H59),"") -> 0 | L59: =IFERROR((J59*H59),"") -> 0
I60: 0 | J60: =ROUNDDOWN(I60*1.1,0) -> 0 | K60: =IFERROR((I60*H60),"") -> 0 | L60: =IFERROR((J60*H60),"") -> 0
I61: 0 | J61: =ROUNDDOWN(I61*1.1,0) -> 0 | K61: =IFERROR((I61*H61),"") -> 0 | L61: =IFERROR((J61*H61),"") -> 0
I62: 0 | J62: =ROUNDDOWN(I62*1.1,0) -> 0 | K62: =IFERROR((I62*H62),"") -> 0 | L62: =IFERROR((J62*H62),"") -> 0
I63: 0 | J63: =ROUNDDOWN(I63*1.1,0) -> 0 | K63: =IFERROR((I63*H63),"") -> 0 | L63: =IFERROR((J63*H63),"") -> 0
A64: =LENB(D64) -> 0 | B64: =LENB(E64) -> 0 | K64: =SUM(K65:K72) -> 0 | L64: =SUM(L65:L72) -> 0 | M64: =ROUNDUP(N64/1.1,0) -> 0 | O64: =ROUNDUP(P64/1.1,0) -> 0 | Q64: =1-(N64/L64) -> #DIV/0! | R64: =K64-M64 -> 0 | S64: =L64-N64 -> 0 | T64: =1-(P64/N64) -> #DIV/0! | U64: =M64-O64 -> 0 | V64: =N64-P64 -> 0 | W64: =ROUNDUP(X64/1.1,0) -> 0
I65: 0 | J65: =ROUNDDOWN(I65*1.1,0) -> 0 | K65: =IFERROR((I65*H65),"") -> 0 | L65: =IFERROR((J65*H65),"") -> 0
I66: 0 | J66: =ROUNDDOWN(I66*1.1,0) -> 0 | K66: =IFERROR((I66*H66),"") -> 0 | L66: =IFERROR((J66*H66),"") -> 0
I67: 0 | J67: =ROUNDDOWN(I67*1.1,0) -> 0 | K67: =IFERROR((I67*H67),"") -> 0 | L67: =IFERROR((J67*H67),"") -> 0
I68: 0 | J68: =ROUNDDOWN(I68*1.1,0) -> 0 | K68: =IFERROR((I68*H68),"") -> 0 | L68: =IFERROR((J68*H68),"") -> 0
I69: 0 | J69: =ROUNDDOWN(I69*1.1,0) -> 0 | K69: =IFERROR((I69*H69),"") -> 0 | L69: =IFERROR((J69*H69),"") -> 0
I70: 0 | J70: =ROUNDDOWN(I70*1.1,0) -> 0 | K70: =IFERROR((I70*H70),"") -> 0 | L70: =IFERROR((J70*H70),"") -> 0
I71: 0 | J71: =ROUNDDOWN(I71*1.1,0) -> 0 | K71: =IFERROR((I71*H71),"") -> 0 | L71: =IFERROR((J71*H71),"") -> 0
I72: 0 | J72: =ROUNDDOWN(I72*1.1,0) -> 0 | K72: =IFERROR((I72*H72),"") -> 0 | L72: =IFERROR((J72*H72),"") -> 0
B74: 【メイン販売オファー：主商品（2枚セットなど）】

Sheet VU_FMT
B1: 施策名：【商品G】●●キャンペーン
B2: ＜対応パターン＞ | E2: ＜KUROSHIO MD用のスコアルール＞
B3: ・新規取得 | E3: ・スコア・・・オファーしたい順に１から数を増やす
B4: ・B行追加 | E4: ※SP用：紐づけ済みのVU商品を外す場合は、有効終了日時を過去にする
B5: ・E行追加 | E5: ＜VU表示＞
B6: ・割引率変更 | E6: ・スマホのVUは最大8個までしか表示されない。
B7: ※変更の場合は、変更点が分かるようにセルを黄色にし、変更内容をメモしてください。 | E7: ・PCの場合は2ページ、3ページと8個以上の表示可能。
B8: ※SP用：順番＆スクリプト変更は、デザイナーが行う＝SJOSPには依頼が来ない。
G11: MOG | H11: MOG
G12: toTCI
B13: ★入力 | C13: ★入力 | D13: プルダウン | E13: ★入力 | F13: ★入力 | G13: ★入力 | H13: ★入力 | I13: ★入力 | J13: ★入力 | K13: ★入力 | L13: ★入力 | M13: デザインチームが、TCIに依頼する原稿
B14: ベース商品 商品コード | C14: ベース商品 商品名 | D14: バリューアップ種類選択 | E14: バリューアップセル 商品コード | F14: バリューアップセル 商品名 | G14: 購入前 | H14: 購入後 | I14: 通常価格 (税込) | J14: 割引後価格 （税込） | K14: 割引率（額） | L14: スコア | M14: サイトスクリプト

Sheet アップグレード
A1: UPG情報まとめ
A2: ベース商品コード | C2: UPG商品コード
A3: 商品コード | B3: 商品コード名 | C3: 商品コード | D3: 商品コード名

Sheet 関連リンク
A1: ■SKUごとの単品価格
A2: \\svdw03jpawscv\Data\SKU\SKU情報追加入力.xlsx
A14: ■承認者フロー
A15: \\filesrv\Projects\1402_0005_SJ共有\Channel Promotion【C】\06_Merchandising meeting\コンカー承認者一覧\20230313_Concur承認者一覧.xlsx

Sheet 変更履歴
A1: ■20231116改定
A2: NO | B2: 内容 | C2: 備考
A3: 1 | B3: 「記入例」タブ削除 | C3: 皆様慣れてきたと思うので、フォーマットからは削除します
A4: 2 | B4: 「単品価格・サイズ・カラバリ情報」タブ削除 | C4: 取得コード情報はすべて「オファーリスト」タブに記載ください
A5: 3 | B5: 「関連商品（バリューアップ）」タブ削除 | C5: 取得コード情報はすべて「オファーリスト」タブで管理・VU価格もこちらに記入するため
